metamart_cli/__init__.py
metamart_cli/api/__init__.py
metamart_cli/api/callbacks.py
metamart_cli/api/config/__init__.py
metamart_cli/api/config/config.py
metamart_cli/api/config/set.py
metamart_cli/api/config/setup.py
metamart_cli/api/demo/__init__.py
metamart_cli/api/demo/endpoints.py
metamart_cli/api/demo/setup.py
metamart_cli/api/entrypoint.py
metamart_cli/api/server/__init__.py
metamart_cli/api/server/endpoints.py
metamart_cli/api/server/setup.py
metamart_cli/api/setup.py
metamart_cli/api/telemetry/__init__.py
metamart_cli/api/telemetry/commands.py
metamart_cli/config_default.yaml
metamart_cli/py.typed
metamart_cli/settings/__init__.py
metamart_cli/settings/cache.py
metamart_cli/settings/config.py
metamart_cli/utilities/__init__.py
metamart_cli/utilities/headers.py
metamart_cli/utilities/serializers.py
metamart_cli/utilities/styling.py
metamart_cli/utilities/telemetry.py
metamart_cli/utilities/test.py
metamart_cli/utilities/utilities.py
metamart_cli/utilities/validators.py
metamart_cli-0.2.7.dist-info/METADATA
metamart_cli-0.2.7.dist-info/WHEEL
metamart_cli-0.2.7.dist-info/entry_points.txt
metamart_cli-0.2.7.dist-info/RECORD
